jc3000/Note.py
jc3000/Sequence.py
jc3000/__init__.py
jc3000-0.0.7.dist-info/LICENSE
jc3000-0.0.7.dist-info/METADATA
jc3000-0.0.7.dist-info/WHEEL
jc3000-0.0.7.dist-info/top_level.txt
jc3000-0.0.7.dist-info/RECORD
