Metadata-Version: 2.1
Name: jc3000
Version: 0.0.7
Summary: A small python package for generating music.
Home-page: https://github.com/reesporte/jc3000
Author: Reese Porter
Author-email: reesedporter@gmail.com
License: UNKNOWN
Project-URL: Bug Tracker, https://github.com/reesporte/jc3000/issues
Platform: UNKNOWN
Classifier: Programming Language :: Python :: 3
Classifier: License :: OSI Approved :: MIT License
Classifier: Operating System :: OS Independent
Requires-Python: >=3.6
License-File: LICENSE
Requires-Dist: numpy
